littlelog/__init__.py
littlelog/littlelog.py
littlelog-0.1.1.dist-info/METADATA
littlelog-0.1.1.dist-info/WHEEL
littlelog-0.1.1.dist-info/top_level.txt
littlelog-0.1.1.dist-info/RECORD
